{"openapi":"3.0.1","info":{"title":"OpenAPI definition","version":"v0"},"servers":[{"url":"https://evening-harbor-96341.herokuapp.com","description":"Generated server url"}],"paths":{"/api/resolucoes/{resolucaoId}/respostas":{"get":{"operationId":"findAllByResolucaoLista","parameters":[{"name":"resolucaoId","in":"path","required":true,"schema":{"type":"integer","format":"int64"}},{"name":"pageable","in":"query","required":false,"schema":{"$ref":"#/components/schemas/Pageable"}}],"responses":{"200":{"description":"default response","content":{"*/*":{"schema":{"$ref":"#/components/schemas/PageResposta"}}}}},"tags":["api resolucoes"]}},"/api/respostas/{id}":{"get":{"operationId":"findById","parameters":[{"name":"id","in":"path","required":true,"schema":{"type":"integer","format":"int64"}}],"responses":{"200":{"description":"default response","content":{"*/*":{"schema":{"$ref":"#/components/schemas/Resposta"}}}}},"tags":["api respostas"]}},"/api/login":{"post":{"operationId":"login","requestBody":{"content":{"*/*":{"schema":{"$ref":"#/components/schemas/Credencial"}}}},"responses":{"200":{"description":"default response","content":{"*/*":{"schema":{"$ref":"#/components/schemas/JwtTokenDTO"}}}}},"tags":["api login"]}},"/api/resolucoes":{"get":{"operationId":"findAll","parameters":[{"name":"pageable","in":"query","required":false,"schema":{"$ref":"#/components/schemas/Pageable"}}],"responses":{"200":{"description":"default response","content":{"*/*":{"schema":{"$ref":"#/components/schemas/PageResolucaoLista"}}}}},"tags":["api resolucoes"]}},"/api/resolucoes/{id}":{"get":{"operationId":"findById_Resolucoes","parameters":[{"name":"id","in":"path","required":true,"schema":{"type":"string"}}],"responses":{"200":{"description":"default response","content":{"*/*":{"schema":{"$ref":"#/components/schemas/ResolucaoLista"}}}}},"tags":["api resolucoes"]}},"/api/avaliacoesResposta":{"get":{"operationId":"findAll_AvaliacoesResposta","parameters":[{"name":"pageable","in":"query","required":false,"schema":{"$ref":"#/components/schemas/Pageable"}}],"responses":{"200":{"description":"default response","content":{"*/*":{"schema":{"$ref":"#/components/schemas/PageAvaliacaoRespostaDTO"}}}}},"tags":["api avaliacoesResposta"]},"post":{"operationId":"create","requestBody":{"content":{"*/*":{"schema":{"$ref":"#/components/schemas/AvaliacaoRespostaDTO"}}}},"responses":{"200":{"description":"default response","content":{"*/*":{"schema":{"$ref":"#/components/schemas/AvaliacaoRespostaDTO"}}}}},"tags":["api avaliacoesResposta"]}},"/api/avaliacoesResolucao/{avaliacaoResolucaoListaId}/{respostaId}":{"get":{"operationId":"findByAvaliacaoResolucaoListaAndResposta","parameters":[{"name":"avaliacaoResolucaoListaId","in":"path","required":true,"schema":{"type":"integer","format":"int64"}},{"name":"respostaId","in":"path","required":true,"schema":{"type":"string","format":"uuid"}}],"responses":{"200":{"description":"default response","content":{"*/*":{"schema":{"$ref":"#/components/schemas/AvaliacaoRespostaDTO"}}}}},"tags":["api avaliacoesResolucao"]}},"/api/avaliacoesResolucao/{avaliacaoResolucaoListaId}/respostas":{"get":{"operationId":"findAllByAvaliacaoResolucaoLista","parameters":[{"name":"avaliacaoResolucaoListaId","in":"path","required":true,"schema":{"type":"integer","format":"int64"}},{"name":"pageable","in":"query","required":false,"schema":{"$ref":"#/components/schemas/Pageable"}}],"responses":{"200":{"description":"default response","content":{"*/*":{"schema":{"$ref":"#/components/schemas/PageAvaliacaoRespostaDTO"}}}}},"tags":["api avaliacoesResolucao"]}},"/api/avaliacoesResposta/{id}":{"get":{"operationId":"findById_AvaliacoesResposta","parameters":[{"name":"id","in":"path","required":true,"schema":{"type":"integer","format":"int64"}}],"responses":{"200":{"description":"default response","content":{"*/*":{"schema":{"$ref":"#/components/schemas/AvaliacaoRespostaDTO"}}}}},"tags":["api avaliacoesResposta"]},"put":{"operationId":"update","parameters":[{"name":"id","in":"path","required":true,"schema":{"type":"integer","format":"int64"}}],"requestBody":{"content":{"*/*":{"schema":{"$ref":"#/components/schemas/AvaliacaoRespostaDTO"}}}},"responses":{"200":{"description":"default response","content":{"*/*":{"schema":{"$ref":"#/components/schemas/AvaliacaoRespostaDTO"}}}}},"tags":["api avaliacoesResposta"]}},"/api/avaliacoesResolucao":{"get":{"operationId":"findAll_AvaliacoesResolucao","parameters":[{"name":"pageable","in":"query","required":false,"schema":{"$ref":"#/components/schemas/Pageable"}}],"responses":{"200":{"description":"default response","content":{"*/*":{"schema":{"$ref":"#/components/schemas/PageAvaliacaoResolucaoListaDTO"}}}}},"tags":["api avaliacoesResolucao"]},"post":{"operationId":"create_AvaliacoesResolucao","requestBody":{"content":{"*/*":{"schema":{"$ref":"#/components/schemas/AvaliacaoResolucaoListaDTO"}}}},"responses":{"200":{"description":"default response","content":{"*/*":{"schema":{"$ref":"#/components/schemas/AvaliacaoResolucaoListaDTO"}}}}},"tags":["api avaliacoesResolucao"]}},"/api/avaliacoesResolucao/minhas":{"get":{"operationId":"listMinhasListas","parameters":[{"name":"pageable","in":"query","required":false,"schema":{"$ref":"#/components/schemas/Pageable"}}],"responses":{"200":{"description":"default response","content":{"*/*":{"schema":{"$ref":"#/components/schemas/PageAvaliacaoResolucaoListaDTO"}}}}},"tags":["api avaliacoesResolucao"]}},"/api/avaliacoesResolucao/paraAvaliar":{"get":{"operationId":"listListasParaAvaliar","parameters":[{"name":"pageable","in":"query","required":false,"schema":{"$ref":"#/components/schemas/Pageable"}}],"responses":{"200":{"description":"default response","content":{"*/*":{"schema":{"$ref":"#/components/schemas/PageAvaliacaoResolucaoListaDTO"}}}}},"tags":["api avaliacoesResolucao"]}},"/api/avaliacoesResolucao/{id}":{"get":{"operationId":"findById_AvaliacoesResolucao","parameters":[{"name":"id","in":"path","required":true,"schema":{"type":"integer","format":"int64"}}],"responses":{"200":{"description":"default response","content":{"*/*":{"schema":{"$ref":"#/components/schemas/AvaliacaoResolucaoListaDTO"}}}}},"tags":["api avaliacoesResolucao"]},"put":{"operationId":"update_AvaliacoesResolucao","parameters":[{"name":"id","in":"path","required":true,"schema":{"type":"integer","format":"int64"}}],"requestBody":{"content":{"*/*":{"schema":{"$ref":"#/components/schemas/AvaliacaoResolucaoListaDTO"}}}},"responses":{"200":{"description":"default response","content":{"*/*":{"schema":{"$ref":"#/components/schemas/AvaliacaoResolucaoListaDTO"}}}}},"tags":["api avaliacoesResolucao"]}},"/api/avaliacoes":{"get":{"operationId":"findAll_Avaliacoes","parameters":[{"name":"pageable","in":"query","required":false,"schema":{"$ref":"#/components/schemas/Pageable"}}],"responses":{"200":{"description":"default response","content":{"*/*":{"schema":{"$ref":"#/components/schemas/PageAvaliacaoLista"}}}}},"tags":["api avaliacoes"]},"post":{"operationId":"create_Avaliacoes","requestBody":{"content":{"*/*":{"schema":{"$ref":"#/components/schemas/AvaliacaoLista"}}}},"responses":{"200":{"description":"default response","content":{"*/*":{"schema":{"$ref":"#/components/schemas/AvaliacaoLista"}}}}},"tags":["api avaliacoes"]}},"/api/avaliacoes/{id}/distribua":{"put":{"operationId":"distribuaListas","parameters":[{"name":"id","in":"path","required":true,"schema":{"type":"integer","format":"int64"}}],"responses":{"200":{"description":"default response","content":{"*/*":{"schema":{"type":"array","items":{"$ref":"#/components/schemas/AvaliacaoResolucaoLista"}}}}}},"tags":["api avaliacoes"]}},"/api/avaliacoes/{id}":{"get":{"operationId":"findById_Avaliacoes","parameters":[{"name":"id","in":"path","required":true,"schema":{"type":"integer","format":"int64"}}],"responses":{"200":{"description":"default response","content":{"*/*":{"schema":{"$ref":"#/components/schemas/AvaliacaoLista"}}}}},"tags":["api avaliacoes"]},"put":{"operationId":"update_Avaliacoes","parameters":[{"name":"id","in":"path","required":true,"schema":{"type":"integer","format":"int64"}}],"requestBody":{"content":{"*/*":{"schema":{"$ref":"#/components/schemas/AvaliacaoLista"}}}},"responses":{"200":{"description":"default response","content":{"*/*":{"schema":{"$ref":"#/components/schemas/AvaliacaoLista"}}}}},"tags":["api avaliacoes"]}}},"components":{"schemas":{"Pageable":{"type":"object","properties":{"sort":{"$ref":"#/components/schemas/Sort"},"pageSize":{"type":"integer","format":"int32"},"pageNumber":{"type":"integer","format":"int32"},"paged":{"type":"boolean"},"unpaged":{"type":"boolean"},"offset":{"type":"integer","format":"int64"}}},"Sort":{"type":"object","properties":{"sorted":{"type":"boolean"},"unsorted":{"type":"boolean"},"empty":{"type":"boolean"}}},"AplicacaoLista":{"required":["lista","turma"],"type":"object","properties":{"id":{"type":"string","format":"uuid"},"lista":{"$ref":"#/components/schemas/Lista"},"turma":{"$ref":"#/components/schemas/Turma"},"resolucoes":{"type":"array","items":{"$ref":"#/components/schemas/ResolucaoLista"}}}},"AreaConhecimento":{"type":"object","properties":{"id":{"type":"integer","format":"int64"},"codigo":{"type":"string"},"nome":{"type":"string"}}},"Discente":{"required":["email","nome"],"type":"object","properties":{"id":{"type":"string"},"nome":{"type":"string"},"email":{"type":"string"},"senha":{"type":"string"},"authorities":{"type":"array","items":{"$ref":"#/components/schemas/SimpleGrantedAuthority"}},"password":{"type":"string"},"username":{"type":"string"},"accountNonExpired":{"type":"boolean"},"accountNonLocked":{"type":"boolean"},"credentialsNonExpired":{"type":"boolean"},"enabled":{"type":"boolean"}}},"Disciplina":{"required":["codigo","id","nome"],"type":"object","properties":{"id":{"type":"string","format":"uuid"},"codigo":{"type":"string"},"nome":{"type":"string"}}},"Docente":{"required":["email","nome"],"type":"object","properties":{"id":{"type":"string"},"nome":{"type":"string"},"email":{"type":"string"},"senha":{"type":"string"},"authorities":{"type":"array","items":{"$ref":"#/components/schemas/SimpleGrantedAuthority"}},"password":{"type":"string"},"username":{"type":"string"},"accountNonExpired":{"type":"boolean"},"accountNonLocked":{"type":"boolean"},"credentialsNonExpired":{"type":"boolean"},"enabled":{"type":"boolean"}}},"Lista":{"type":"object","properties":{"id":{"type":"string","format":"uuid"},"questoes":{"type":"array","items":{"$ref":"#/components/schemas/Questao"}},"usuarioCadastro":{"type":"string"}}},"PageResposta":{"type":"object","properties":{"totalPages":{"type":"integer","format":"int32"},"totalElements":{"type":"integer","format":"int64"},"first":{"type":"boolean"},"sort":{"$ref":"#/components/schemas/Sort"},"number":{"type":"integer","format":"int32"},"numberOfElements":{"type":"integer","format":"int32"},"last":{"type":"boolean"},"pageable":{"$ref":"#/components/schemas/Pageable"},"size":{"type":"integer","format":"int32"},"content":{"type":"array","items":{"$ref":"#/components/schemas/Resposta"}},"empty":{"type":"boolean"}}},"Questao":{"type":"object","properties":{"id":{"type":"string","format":"uuid"},"enunciado":{"type":"string"},"areaConhecimento":{"$ref":"#/components/schemas/AreaConhecimento"},"palavrasChave":{"type":"array","items":{"type":"string"}}}},"ResolucaoLista":{"type":"object","properties":{"id":{"type":"string","format":"uuid"},"aplicacaoLista":{"$ref":"#/components/schemas/AplicacaoLista"},"discente":{"$ref":"#/components/schemas/Discente"}}},"Resposta":{"type":"object","properties":{"id":{"type":"string","format":"uuid"},"resolucaoLista":{"$ref":"#/components/schemas/ResolucaoLista"},"questao":{"$ref":"#/components/schemas/Questao"},"conteudo":{"type":"string"}}},"SimpleGrantedAuthority":{"type":"object","properties":{"authority":{"type":"string"}}},"Turma":{"required":["disciplina","docente","semestre"],"type":"object","properties":{"id":{"type":"string","format":"uuid"},"disciplina":{"$ref":"#/components/schemas/Disciplina"},"semestre":{"type":"string"},"docente":{"$ref":"#/components/schemas/Docente"},"discentes":{"uniqueItems":true,"type":"array","items":{"$ref":"#/components/schemas/Discente"}}}},"Credencial":{"type":"object","properties":{"email":{"type":"string"},"senha":{"type":"string"}}},"JwtTokenDTO":{"type":"object","properties":{"email":{"type":"string"},"token":{"type":"string"},"role":{"type":"string"}}},"PageResolucaoLista":{"type":"object","properties":{"totalPages":{"type":"integer","format":"int32"},"totalElements":{"type":"integer","format":"int64"},"first":{"type":"boolean"},"sort":{"$ref":"#/components/schemas/Sort"},"number":{"type":"integer","format":"int32"},"numberOfElements":{"type":"integer","format":"int32"},"last":{"type":"boolean"},"pageable":{"$ref":"#/components/schemas/Pageable"},"size":{"type":"integer","format":"int32"},"content":{"type":"array","items":{"$ref":"#/components/schemas/ResolucaoLista"}},"empty":{"type":"boolean"}}},"AvaliacaoResolucaoLista":{"type":"object","properties":{"id":{"type":"integer","format":"int64"},"resolucaoListaId":{"type":"string","format":"uuid"},"discenteId":{"type":"string"},"avaliadorId":{"type":"string"},"publicada":{"type":"boolean"},"nota":{"type":"number","format":"float"},"dataCadastro":{"type":"string","format":"date-time"},"usuarioCadastro":{"type":"string"},"dataAlteracao":{"type":"string","format":"date-time"},"usuarioAlteracao":{"type":"string"}}},"AvaliacaoResolucaoListaDTO":{"type":"object","properties":{"id":{"type":"integer","format":"int64"},"resolucaoListaId":{"type":"string","format":"uuid"},"discenteId":{"type":"string"},"avaliadorId":{"type":"string"},"publicada":{"type":"boolean"},"nota":{"type":"number","format":"float"},"avaliacoesRespostasSaved":{"type":"array","items":{"$ref":"#/components/schemas/AvaliacaoResposta"}},"dataCadastro":{"type":"string","format":"date-time"},"usuarioCadastro":{"type":"string"},"dataAlteracao":{"type":"string","format":"date-time"},"usuarioAlteracao":{"type":"string"},"resolucaoLista":{"$ref":"#/components/schemas/ResolucaoLista"},"avaliador":{"$ref":"#/components/schemas/Usuario"}}},"AvaliacaoResposta":{"type":"object","properties":{"id":{"type":"integer","format":"int64"},"avaliacaoResolucaoLista":{"$ref":"#/components/schemas/AvaliacaoResolucaoLista"},"respostaId":{"type":"string","format":"uuid"},"avaliadorId":{"type":"string"},"comentario":{"type":"string"},"nota":{"type":"number","format":"float"},"publicada":{"type":"boolean"},"dataCadastro":{"type":"string","format":"date-time"},"dataAlteracao":{"type":"string","format":"date-time"}}},"AvaliacaoRespostaDTO":{"type":"object","properties":{"id":{"type":"integer","format":"int64"},"avaliacaoResolucaoLista":{"$ref":"#/components/schemas/AvaliacaoResolucaoListaDTO"},"respostaId":{"type":"string","format":"uuid"},"avaliadorId":{"type":"string"},"comentario":{"type":"string"},"nota":{"type":"number","format":"float"},"publicada":{"type":"boolean"},"dataCadastro":{"type":"string","format":"date-time"},"dataAlteracao":{"type":"string","format":"date-time"},"resposta":{"$ref":"#/components/schemas/Resposta"},"avaliador":{"$ref":"#/components/schemas/Usuario"}}},"PageAvaliacaoRespostaDTO":{"type":"object","properties":{"totalPages":{"type":"integer","format":"int32"},"totalElements":{"type":"integer","format":"int64"},"first":{"type":"boolean"},"sort":{"$ref":"#/components/schemas/Sort"},"number":{"type":"integer","format":"int32"},"numberOfElements":{"type":"integer","format":"int32"},"last":{"type":"boolean"},"pageable":{"$ref":"#/components/schemas/Pageable"},"size":{"type":"integer","format":"int32"},"content":{"type":"array","items":{"$ref":"#/components/schemas/AvaliacaoRespostaDTO"}},"empty":{"type":"boolean"}}},"Usuario":{"required":["dtype","email","nome"],"type":"object","properties":{"id":{"type":"string"},"nome":{"type":"string"},"email":{"type":"string"},"senha":{"type":"string"},"authorities":{"type":"array","items":{"$ref":"#/components/schemas/SimpleGrantedAuthority"}},"password":{"type":"string"},"username":{"type":"string"},"accountNonExpired":{"type":"boolean"},"accountNonLocked":{"type":"boolean"},"credentialsNonExpired":{"type":"boolean"},"enabled":{"type":"boolean"},"dtype":{"type":"string"}},"discriminator":{"propertyName":"dtype"}},"PageAvaliacaoResolucaoListaDTO":{"type":"object","properties":{"totalPages":{"type":"integer","format":"int32"},"totalElements":{"type":"integer","format":"int64"},"first":{"type":"boolean"},"sort":{"$ref":"#/components/schemas/Sort"},"number":{"type":"integer","format":"int32"},"numberOfElements":{"type":"integer","format":"int32"},"last":{"type":"boolean"},"pageable":{"$ref":"#/components/schemas/Pageable"},"size":{"type":"integer","format":"int32"},"content":{"type":"array","items":{"$ref":"#/components/schemas/AvaliacaoResolucaoListaDTO"}},"empty":{"type":"boolean"}}},"AvaliacaoLista":{"required":["aplicacaoListaId","criterioAvaliacao","distribuida"],"type":"object","properties":{"id":{"type":"integer","format":"int64"},"aplicacaoListaId":{"type":"string","format":"uuid"},"avaliadores":{"type":"array","items":{"type":"string","format":"uuid"}},"criterioAvaliacao":{"type":"string","enum":["MESA_REDONDA","FIFO","RANDOMICO"]},"distribuida":{"type":"boolean"},"dataCadastro":{"type":"string","format":"date-time"},"usuarioCadastro":{"type":"string"},"dataAlteracao":{"type":"string","format":"date-time"},"usuarioAlteracao":{"type":"string"}}},"PageAvaliacaoLista":{"type":"object","properties":{"totalPages":{"type":"integer","format":"int32"},"totalElements":{"type":"integer","format":"int64"},"first":{"type":"boolean"},"sort":{"$ref":"#/components/schemas/Sort"},"number":{"type":"integer","format":"int32"},"numberOfElements":{"type":"integer","format":"int32"},"last":{"type":"boolean"},"pageable":{"$ref":"#/components/schemas/Pageable"},"size":{"type":"integer","format":"int32"},"content":{"type":"array","items":{"$ref":"#/components/schemas/AvaliacaoLista"}},"empty":{"type":"boolean"}}}}}}
